{"GREE": {"ticker": "GREE", "entry_time": "2025-11-26T17:34:00-05:00", "entry_price": 1.5625, "exit_time": "2025-11-26T17:58:00-05:00", "exit_price": 1.546875, "sentiment": "positive", "return": -0.01}, "OMC": {"ticker": "OMC", "entry_time": "2025-11-26T18:36:00-05:00", "entry_price": 71.5, "exit_time": "2025-11-26T18:36:00-05:00", "exit_price": 71.5, "sentiment": "positive", "return": 0.0}, "PFLT": {"ticker": "PFLT", "entry_time": "2025-11-26T17:59:00-05:00", "entry_price": 9.2, "exit_time": "2025-11-26T17:59:00-05:00", "exit_price": 9.2, "sentiment": "positive", "return": 0.0}}